main.py
segmentmesher/__init__.py
segmentmesher/geometry.py
segmentmesher/mesh.py
segmentmesher/test_data.py
segmentmesher-0.1.1.dist-info/METADATA
segmentmesher-0.1.1.dist-info/WHEEL
segmentmesher-0.1.1.dist-info/entry_points.txt
segmentmesher-0.1.1.dist-info/top_level.txt
segmentmesher-0.1.1.dist-info/RECORD
