Metadata-Version: 2.4
Name: segmentmesher
Version: 0.1.1
Summary: Add your description here
Requires-Python: >=3.11
Requires-Dist: click>=8.1.8
Requires-Dist: numpy>=2.1.2
Requires-Dist: pillow>=11.0.0
Requires-Dist: pyvista[all]>=0.44.1
Requires-Dist: scikit-image>=0.24.0
Requires-Dist: wildmeshing>=0.4
